serviceconnect/__init__.py
serviceconnect/bus.py
serviceconnect/settings.py
serviceconnect/utils.py
serviceconnect-0.1.dist-info/LICENSE
serviceconnect-0.1.dist-info/METADATA
serviceconnect-0.1.dist-info/WHEEL
serviceconnect-0.1.dist-info/top_level.txt
serviceconnect-0.1.dist-info/RECORD
